msfiddle/__init__.py
msfiddle/dataset.py
msfiddle/download.py
msfiddle/main.py
msfiddle/model_tcn.py
msfiddle/config/fiddle_tcn_casmi.yml
msfiddle/config/fiddle_tcn_demo.yml
msfiddle/config/fiddle_tcn_demo_wo_da.yml
msfiddle/config/fiddle_tcn_embl.yml
msfiddle/config/fiddle_tcn_orbitrap.yml
msfiddle/config/fiddle_tcn_qtof.yml
msfiddle/demo/input_msms.mgf
msfiddle/demo/output_buddy.csv
msfiddle/demo/output_fiddle.csv
msfiddle/demo/output_fiddle_all.csv
msfiddle/demo/output_sirius.csv
msfiddle/utils/__init__.py
msfiddle/utils/mol_utils.py
msfiddle/utils/msms_utils.py
msfiddle/utils/pkl_utils.py
msfiddle/utils/refine_utils.py
msfiddle-0.1.0.dist-info/licenses/LICENSE
msfiddle-0.1.0.dist-info/METADATA
msfiddle-0.1.0.dist-info/WHEEL
msfiddle-0.1.0.dist-info/entry_points.txt
msfiddle-0.1.0.dist-info/top_level.txt
msfiddle-0.1.0.dist-info/RECORD
