Metadata-Version: 2.4
Name: msfiddle
Version: 0.1.0
Summary: A package for predicting chemical formulas from tandem mass spectra
Home-page: https://github.com/JosieHong/msfiddle
Author: Yuhui Hong
Author-email: josieexception@outlook.com
Classifier: Programming Language :: Python :: 3
Classifier: License :: OSI Approved :: GNU Affero General Public License v3
Classifier: Operating System :: OS Independent
Classifier: Topic :: Scientific/Engineering :: Chemistry
Classifier: Topic :: Scientific/Engineering :: Artificial Intelligence
Classifier: Topic :: Scientific/Engineering :: Bio-Informatics
Classifier: Topic :: Scientific/Engineering :: Medical Science Apps.
Requires-Python: >=3.6
License-File: LICENSE
Requires-Dist: numpy<2.0.0,>=1.20.0
Requires-Dist: pandas>=2.0.0
Requires-Dist: tqdm>=4.60.0
Requires-Dist: pyyaml>=6.0
Requires-Dist: scikit-learn>=1.0.0
Requires-Dist: scipy>=1.8.0
Requires-Dist: pyarrow>=10.0.0
Requires-Dist: rdkit>=2022.03.5
Requires-Dist: molmass
Requires-Dist: pyteomics
Dynamic: author
Dynamic: author-email
Dynamic: classifier
Dynamic: description
Dynamic: description-content-type
Dynamic: home-page
Dynamic: license-file
Dynamic: requires-dist
Dynamic: requires-python
Dynamic: summary
